ategpt/__init__.py
ategpt/ategpt.py
ategpt-1.0.0.dist-info/LICENSE
ategpt-1.0.0.dist-info/METADATA
ategpt-1.0.0.dist-info/WHEEL
ategpt-1.0.0.dist-info/top_level.txt
ategpt-1.0.0.dist-info/RECORD
