Metadata-Version: 2.1
Name: ategpt
Version: 1.0.0
Summary: ATE-GPT ('Ask, Think, Evaluate', powered by GPT) is a lightweight module for guiding a GPT-based LLM through a comprehensive thought process on any subject.
Author-email: David Mays <maysidavid@gmail.com>
Project-URL: Homepage, https://github.com/dimays/ategpt
Project-URL: Bug Tracker, https://github.com/dimays/ategpt/issues
Classifier: Programming Language :: Python :: 3
Classifier: License :: OSI Approved :: MIT License
Classifier: Operating System :: OS Independent
Requires-Python: >=3.7.1
License-File: LICENSE
Requires-Dist: aiohttp ==3.8.5
Requires-Dist: aiosignal ==1.3.1
Requires-Dist: async-timeout ==4.0.3
Requires-Dist: attrs ==23.1.0
Requires-Dist: bleach ==6.0.0
Requires-Dist: build ==1.0.0
Requires-Dist: certifi ==2023.7.22
Requires-Dist: charset-normalizer ==3.2.0
Requires-Dist: docutils ==0.20.1
Requires-Dist: frozenlist ==1.4.0
Requires-Dist: idna ==3.4
Requires-Dist: importlib-metadata ==6.8.0
Requires-Dist: jaraco.classes ==3.3.0
Requires-Dist: keyring ==24.2.0
Requires-Dist: markdown-it-py ==3.0.0
Requires-Dist: mdurl ==0.1.2
Requires-Dist: more-itertools ==10.1.0
Requires-Dist: multidict ==6.0.4
Requires-Dist: openai ==0.28.0
Requires-Dist: packaging ==23.1
Requires-Dist: pkginfo ==1.9.6
Requires-Dist: Pygments ==2.16.1
Requires-Dist: pyproject-hooks ==1.0.0
Requires-Dist: readme-renderer ==41.0
Requires-Dist: requests ==2.31.0
Requires-Dist: requests-toolbelt ==1.0.0
Requires-Dist: rfc3986 ==2.0.0
Requires-Dist: rich ==13.5.2
Requires-Dist: six ==1.16.0
Requires-Dist: tomli ==2.0.1
Requires-Dist: tqdm ==4.66.1
Requires-Dist: twine ==4.0.2
Requires-Dist: urllib3 ==2.0.4
Requires-Dist: webencodings ==0.5.1
Requires-Dist: yarl ==1.9.2
Requires-Dist: zipp ==3.16.2
